AcisCanTools.py
tools/plotting/excel-NOx.py
tools/plotting/filterPlot.py
tools/plotting/plotFFT.py
tools/plotting/signalGen.py
aciscantools-0.1.4.1.dist-info/METADATA
aciscantools-0.1.4.1.dist-info/WHEEL
aciscantools-0.1.4.1.dist-info/top_level.txt
aciscantools-0.1.4.1.dist-info/RECORD
