Metadata-Version: 2.4
Name: AcisCanTools
Version: 0.1.4.1
Summary: A Python toolkit for logging, parsing, simulating, visualizing, and analyzing CAN (Controller Area Network) data.
Requires-Python: >=3.12
Requires-Dist: matplotlib>=3.10.3
Requires-Dist: pandas>=2.3.0
Requires-Dist: python-can>=4.5.0
